nbexfeedback_pkg/__init__.py
nbexfeedback_pkg/example.py
nbexfeedback-0.0.2.dist-info/LICENSE
nbexfeedback-0.0.2.dist-info/METADATA
nbexfeedback-0.0.2.dist-info/WHEEL
nbexfeedback-0.0.2.dist-info/top_level.txt
nbexfeedback-0.0.2.dist-info/RECORD
