Metadata-Version: 2.1
Name: nbexfeedback
Version: 0.0.2
Summary: Error feedback form for Jupyter notebooks
Home-page: UNKNOWN
Author: Blueprint (Andi Halim)
Author-email: <andihalim@berkeley.edu>
License: UNKNOWN
Keywords: python,form,feedback
Platform: UNKNOWN
Classifier: Development Status :: 1 - Planning
Classifier: Intended Audience :: Developers
Classifier: Programming Language :: Python :: 3
Classifier: Operating System :: Unix
Classifier: Operating System :: MacOS :: MacOS X
Classifier: Operating System :: Microsoft :: Windows
License-File: LICENSE
